[
    {
        "id": 1253609114,
        "objectid": 249600,
        "date": "2024-06-17",
        "activitytype": "pageviews",
        "activitycount": 1,
        "lastupdate": "2024-06-18T06:16:45-0400"
    },
    {
        "id": 1258658972,
        "objectid": 160274,
        "date": "2024-06-17",
        "activitytype": "pageviews",
        "activitycount": 3,
        "lastupdate": "2024-06-18T06:16:45-0400"
    },
    {
        "id": 20603756,
        "objectid": 345760,
        "date": "2024-06-17",
        "activitytype": "uniquepageviews",
        "activitycount": 1,
        "lastupdate": "2024-06-18T06:16:45-0400"
    },
    {
        "id": 14540652,
        "objectid": 303388,
        "date": "2024-06-17",
        "activitytype": "uniquepageviews",
        "activitycount": 1,
        "lastupdate": "2024-06-18T06:16:45-0400"
    },
    {
        "id": 1256792474,
        "objectid": 237231,
        "date": "2024-06-17",
        "activitytype": "pageviews",
        "activitycount": 1,
        "lastupdate": "2024-06-18T06:16:45-0400"
    },
    {
        "id": 1256597658,
        "objectid": 233894,
        "date": "2024-06-17",
        "activitytype": "pageviews",
        "activitycount": 1,
        "lastupdate": "2024-06-18T06:16:45-0400"
    },
    {
        "id": 20774764,
        "objectid": 344124,
        "date": "2024-06-17",
        "activitytype": "uniquepageviews",
        "activitycount": 1,
        "lastupdate": "2024-06-18T06:16:45-0400"
    },
    {
        "id": 129269356,
        "objectid": 247997,
        "date": "2024-06-17",
        "activitytype": "uniquepageviews",
        "activitycount": 1,
        "lastupdate": "2024-06-18T06:16:45-0400"
    },
    {
        "id": 1295195802,
        "objectid": 279696,
        "date": "2024-06-17",
        "activitytype": "pageviews",
        "activitycount": 1,
        "lastupdate": "2024-06-18T06:16:45-0400"
    },
    {
        "id": 132512364,
        "objectid": 235833,
        "date": "2024-06-17",
        "activitytype": "uniquepageviews",
        "activitycount": 1,
        "lastupdate": "2024-06-18T06:16:45-0400"
    },
    {
        "id": 7497836,
        "objectid": 265899,
        "date": "2024-06-17",
        "activitytype": "uniquepageviews",
        "activitycount": 1,
        "lastupdate": "2024-06-18T06:16:45-0400"
    },
    {
        "id": 21164908,
        "objectid": 343600,
        "date": "2024-06-17",
        "activitytype": "uniquepageviews",
        "activitycount": 1,
        "lastupdate": "2024-06-18T06:16:45-0400"
    },
    {
        "id": 19971436,
        "objectid": 347262,
        "date": "2024-06-17",
        "activitytype": "uniquepageviews",
        "activitycount": 1,
        "lastupdate": "2024-06-18T06:16:45-0400"
    },
    {
        "id": 130816108,
        "objectid": 241883,
        "date": "2024-06-17",
        "activitytype": "uniquepageviews",
        "activitycount": 1,
        "lastupdate": "2024-06-18T06:16:45-0400"
    },
    {
        "id": 110728556,
        "objectid": 189782,
        "date": "2024-06-17",
        "activitytype": "uniquepageviews",
        "activitycount": 1,
        "lastupdate": "2024-06-18T06:16:45-0400"
    },
    {
        "id": 133430636,
        "objectid": 233278,
        "date": "2024-06-17",
        "activitytype": "uniquepageviews",
        "activitycount": 1,
        "lastupdate": "2024-06-18T06:16:45-0400"
    },
    {
        "id": 129047916,
        "objectid": 249310,
        "date": "2024-06-17",
        "activitytype": "uniquepageviews",
        "activitycount": 1,
        "lastupdate": "2024-06-18T06:16:46-0400"
    },
    {
        "id": 13377388,
        "objectid": 307420,
        "date": "2024-06-17",
        "activitytype": "uniquepageviews",
        "activitycount": 1,
        "lastupdate": "2024-06-18T06:16:46-0400"
    },
    {
        "id": 1256066458,
        "objectid": 240003,
        "date": "2024-06-17",
        "activitytype": "pageviews",
        "activitycount": 1,
        "lastupdate": "2024-06-18T06:16:46-0400"
    },
    {
        "id": 20838764,
        "objectid": 344378,
        "date": "2024-06-17",
        "activitytype": "uniquepageviews",
        "activitycount": 1,
        "lastupdate": "2024-06-18T06:16:46-0400"
    },
    {
        "id": 1524076,
        "objectid": 289666,
        "date": "2024-06-17",
        "activitytype": "uniquepageviews",
        "activitycount": 1,
        "lastupdate": "2024-06-18T06:16:46-0400"
    },
    {
        "id": 5189996,
        "objectid": 275442,
        "date": "2024-06-17",
        "activitytype": "uniquepageviews",
        "activitycount": 1,
        "lastupdate": "2024-06-18T06:16:46-0400"
    },
    {
        "id": 1248490652,
        "objectid": 204282,
        "date": "2024-06-17",
        "activitytype": "pageviews",
        "activitycount": 3,
        "lastupdate": "2024-06-18T06:16:46-0400"
    },
    {
        "id": 68349804,
        "objectid": 28204,
        "date": "2024-06-17",
        "activitytype": "uniquepageviews",
        "activitycount": 1,
        "lastupdate": "2024-06-18T06:16:46-0400"
    },
    {
        "id": 1253697434,
        "objectid": 249449,
        "date": "2024-06-17",
        "activitytype": "pageviews",
        "activitycount": 1,
        "lastupdate": "2024-06-18T06:16:46-0400"
    },
    {
        "id": 17900140,
        "objectid": 355809,
        "date": "2024-06-17",
        "activitytype": "uniquepageviews",
        "activitycount": 1,
        "lastupdate": "2024-06-18T06:16:46-0400"
    },
    {
        "id": 919097114,
        "objectid": 212509,
        "date": "2024-06-17",
        "activitytype": "conservation",
        "activitycount": 1,
        "lastupdate": "2024-06-18T06:16:46-0400"
    },
    {
        "id": 1296341402,
        "objectid": 275223,
        "date": "2024-06-17",
        "activitytype": "pageviews",
        "activitycount": 1,
        "lastupdate": "2024-06-18T06:16:46-0400"
    },
    {
        "id": 4186220,
        "objectid": 279331,
        "date": "2024-06-17",
        "activitytype": "uniquepageviews",
        "activitycount": 1,
        "lastupdate": "2024-06-18T06:16:46-0400"
    },
    {
        "id": 1297670811,
        "objectid": 274284,
        "date": "2024-06-17",
        "activitytype": "pageviews",
        "activitycount": 2,
        "lastupdate": "2024-06-18T06:16:46-0400"
    },
    {
        "id": 130909036,
        "objectid": 241984,
        "date": "2024-06-17",
        "activitytype": "uniquepageviews",
        "activitycount": 1,
        "lastupdate": "2024-06-18T06:16:46-0400"
    },
    {
        "id": 1258030746,
        "objectid": 232328,
        "date": "2024-06-17",
        "activitytype": "pageviews",
        "activitycount": 1,
        "lastupdate": "2024-06-18T06:16:46-0400"
    },
    {
        "id": 1301061786,
        "objectid": 326446,
        "date": "2024-06-17",
        "activitytype": "pageviews",
        "activitycount": 1,
        "lastupdate": "2024-06-18T06:16:46-0400"
    },
    {
        "id": 129123948,
        "objectid": 249477,
        "date": "2024-06-17",
        "activitytype": "uniquepageviews",
        "activitycount": 1,
        "lastupdate": "2024-06-18T06:16:46-0400"
    },
    {
        "id": 131198572,
        "objectid": 240941,
        "date": "2024-06-17",
        "activitytype": "uniquepageviews",
        "activitycount": 1,
        "lastupdate": "2024-06-18T06:16:46-0400"
    },
    {
        "id": 1247410843,
        "objectid": 208500,
        "date": "2024-06-17",
        "activitytype": "pageviews",
        "activitycount": 2,
        "lastupdate": "2024-06-18T06:16:46-0400"
    },
    {
        "id": 1248372122,
        "objectid": 204587,
        "date": "2024-06-17",
        "activitytype": "pageviews",
        "activitycount": 1,
        "lastupdate": "2024-06-18T06:16:46-0400"
    },
    {
        "id": 1279247258,
        "objectid": 346189,
        "date": "2024-06-17",
        "activitytype": "pageviews",
        "activitycount": 1,
        "lastupdate": "2024-06-18T06:16:46-0400"
    },
    {
        "id": 1304913050,
        "objectid": 307434,
        "date": "2024-06-17",
        "activitytype": "pageviews",
        "activitycount": 1,
        "lastupdate": "2024-06-18T06:16:46-0400"
    },
    {
        "id": 11742060,
        "objectid": 315368,
        "date": "2024-06-17",
        "activitytype": "uniquepageviews",
        "activitycount": 1,
        "lastupdate": "2024-06-18T06:16:46-0400"
    },
    {
        "id": 1288817050,
        "objectid": 370247,
        "date": "2024-06-17",
        "activitytype": "pageviews",
        "activitycount": 1,
        "lastupdate": "2024-06-18T06:16:46-0400"
    },
    {
        "id": 1307975066,
        "objectid": 295315,
        "date": "2024-06-17",
        "activitytype": "pageviews",
        "activitycount": 1,
        "lastupdate": "2024-06-18T06:16:46-0400"
    },
    {
        "id": 128925551,
        "objectid": 250876,
        "date": "2024-06-17",
        "activitytype": "uniquepageviews",
        "activitycount": 2,
        "lastupdate": "2024-06-18T06:16:46-0400"
    },
    {
        "id": 119474796,
        "objectid": 222153,
        "date": "2024-06-17",
        "activitytype": "uniquepageviews",
        "activitycount": 1,
        "lastupdate": "2024-06-18T06:16:46-0400"
    },
    {
        "id": 1272983450,
        "objectid": 169889,
        "date": "2024-06-17",
        "activitytype": "pageviews",
        "activitycount": 1,
        "lastupdate": "2024-06-18T06:16:46-0400"
    },
    {
        "id": 13383788,
        "objectid": 307451,
        "date": "2024-06-17",
        "activitytype": "uniquepageviews",
        "activitycount": 1,
        "lastupdate": "2024-06-18T06:16:46-0400"
    },
    {
        "id": 1280221850,
        "objectid": 342316,
        "date": "2024-06-17",
        "activitytype": "pageviews",
        "activitycount": 1,
        "lastupdate": "2024-06-18T06:16:46-0400"
    },
    {
        "id": 1255143322,
        "objectid": 243833,
        "date": "2024-06-17",
        "activitytype": "pageviews",
        "activitycount": 1,
        "lastupdate": "2024-06-18T06:16:46-0400"
    },
    {
        "id": 1283285405,
        "objectid": 330479,
        "date": "2024-06-17",
        "activitytype": "pageviews",
        "activitycount": 4,
        "lastupdate": "2024-06-18T06:16:46-0400"
    },
    {
        "id": 1276134810,
        "objectid": 354251,
        "date": "2024-06-17",
        "activitytype": "pageviews",
        "activitycount": 1,
        "lastupdate": "2024-06-18T06:16:46-0400"
    },
    {
        "id": 198508,
        "objectid": 294852,
        "date": "2024-06-17",
        "activitytype": "uniquepageviews",
        "activitycount": 1,
        "lastupdate": "2024-06-18T06:16:46-0400"
    },
    {
        "id": 128776044,
        "objectid": 249908,
        "date": "2024-06-17",
        "activitytype": "uniquepageviews",
        "activitycount": 1,
        "lastupdate": "2024-06-18T06:16:46-0400"
    },
    {
        "id": 1672279345,
        "objectid": 310699,
        "date": "2024-06-17",
        "activitytype": "moves",
        "activitycount": 1,
        "lastupdate": "2024-06-18T06:16:46-0400"
    },
    {
        "id": 1278393498,
        "objectid": 345394,
        "date": "2024-06-17",
        "activitytype": "pageviews",
        "activitycount": 1,
        "lastupdate": "2024-06-18T06:16:46-0400"
    },
    {
        "id": 125862764,
        "objectid": 261184,
        "date": "2024-06-17",
        "activitytype": "uniquepageviews",
        "activitycount": 1,
        "lastupdate": "2024-06-18T06:16:46-0400"
    },
    {
        "id": 22635116,
        "objectid": 337313,
        "date": "2024-06-17",
        "activitytype": "uniquepageviews",
        "activitycount": 1,
        "lastupdate": "2024-06-18T06:16:46-0400"
    },
    {
        "id": 20029804,
        "objectid": 347490,
        "date": "2024-06-17",
        "activitytype": "uniquepageviews",
        "activitycount": 1,
        "lastupdate": "2024-06-18T06:16:46-0400"
    },
    {
        "id": 133781100,
        "objectid": 230805,
        "date": "2024-06-17",
        "activitytype": "uniquepageviews",
        "activitycount": 1,
        "lastupdate": "2024-06-18T06:16:46-0400"
    },
    {
        "id": 1301135514,
        "objectid": 326222,
        "date": "2024-06-17",
        "activitytype": "pageviews",
        "activitycount": 1,
        "lastupdate": "2024-06-18T06:16:46-0400"
    },
    {
        "id": 1299985818,
        "objectid": 265147,
        "date": "2024-06-17",
        "activitytype": "pageviews",
        "activitycount": 1,
        "lastupdate": "2024-06-18T06:16:46-0400"
    },
    {
        "id": 8763759,
        "objectid": 326010,
        "date": "2024-06-17",
        "activitytype": "uniquepageviews",
        "activitycount": 2,
        "lastupdate": "2024-06-18T06:16:46-0400"
    },
    {
        "id": 7885164,
        "objectid": 263314,
        "date": "2024-06-17",
        "activitytype": "uniquepageviews",
        "activitycount": 1,
        "lastupdate": "2024-06-18T06:16:46-0400"
    },
    {
        "id": 1646947377,
        "objectid": 342834,
        "date": "2024-06-17",
        "activitytype": "moves",
        "activitycount": 1,
        "lastupdate": "2024-06-18T06:16:46-0400"
    },
    {
        "id": 1248364186,
        "objectid": 204552,
        "date": "2024-06-17",
        "activitytype": "pageviews",
        "activitycount": 1,
        "lastupdate": "2024-06-18T06:16:46-0400"
    },
    {
        "id": 1246014618,
        "objectid": 209698,
        "date": "2024-06-17",
        "activitytype": "pageviews",
        "activitycount": 1,
        "lastupdate": "2024-06-18T06:16:46-0400"
    },
    {
        "id": 115681900,
        "objectid": 170473,
        "date": "2024-06-17",
        "activitytype": "uniquepageviews",
        "activitycount": 1,
        "lastupdate": "2024-06-18T06:16:46-0400"
    },
    {
        "id": 122548588,
        "objectid": 209202,
        "date": "2024-06-17",
        "activitytype": "uniquepageviews",
        "activitycount": 1,
        "lastupdate": "2024-06-18T06:16:46-0400"
    },
    {
        "id": 1672287025,
        "objectid": 310349,
        "date": "2024-06-17",
        "activitytype": "moves",
        "activitycount": 1,
        "lastupdate": "2024-06-18T06:16:46-0400"
    },
    {
        "id": 125827948,
        "objectid": 197432,
        "date": "2024-06-17",
        "activitytype": "uniquepageviews",
        "activitycount": 1,
        "lastupdate": "2024-06-18T06:16:46-0400"
    },
    {
        "id": 85326444,
        "objectid": 92473,
        "date": "2024-06-17",
        "activitytype": "uniquepageviews",
        "activitycount": 1,
        "lastupdate": "2024-06-18T06:16:46-0400"
    },
    {
        "id": 133346156,
        "objectid": 233072,
        "date": "2024-06-17",
        "activitytype": "uniquepageviews",
        "activitycount": 1,
        "lastupdate": "2024-06-18T06:16:46-0400"
    },
    {
        "id": 1254530714,
        "objectid": 241936,
        "date": "2024-06-17",
        "activitytype": "pageviews",
        "activitycount": 1,
        "lastupdate": "2024-06-18T06:16:46-0400"
    },
    {
        "id": 127721068,
        "objectid": 253981,
        "date": "2024-06-17",
        "activitytype": "uniquepageviews",
        "activitycount": 1,
        "lastupdate": "2024-06-18T06:16:46-0400"
    },
    {
        "id": 1709867651,
        "objectid": 384353,
        "date": "2024-06-17",
        "activitytype": "studycenterviews",
        "activitycount": 1,
        "lastupdate": "2024-06-18T06:16:46-0400"
    },
    {
        "id": 132263788,
        "objectid": 237292,
        "date": "2024-06-17",
        "activitytype": "uniquepageviews",
        "activitycount": 1,
        "lastupdate": "2024-06-18T06:16:46-0400"
    },
    {
        "id": 128983660,
        "objectid": 249057,
        "date": "2024-06-17",
        "activitytype": "uniquepageviews",
        "activitycount": 1,
        "lastupdate": "2024-06-18T06:16:46-0400"
    },
    {
        "id": 1253681818,
        "objectid": 249380,
        "date": "2024-06-17",
        "activitytype": "pageviews",
        "activitycount": 1,
        "lastupdate": "2024-06-18T06:16:46-0400"
    },
    {
        "id": 126119532,
        "objectid": 260269,
        "date": "2024-06-17",
        "activitytype": "uniquepageviews",
        "activitycount": 1,
        "lastupdate": "2024-06-18T06:16:46-0400"
    },
    {
        "id": 21419116,
        "objectid": 342551,
        "date": "2024-06-17",
        "activitytype": "uniquepageviews",
        "activitycount": 1,
        "lastupdate": "2024-06-18T06:16:46-0400"
    },
    {
        "id": 1695288707,
        "objectid": 343022,
        "date": "2024-06-17",
        "activitytype": "studycenterviews",
        "activitycount": 1,
        "lastupdate": "2024-06-18T06:16:46-0400"
    },
    {
        "id": 84745324,
        "objectid": 94687,
        "date": "2024-06-17",
        "activitytype": "uniquepageviews",
        "activitycount": 1,
        "lastupdate": "2024-06-18T06:16:46-0400"
    },
    {
        "id": 1247462298,
        "objectid": 208205,
        "date": "2024-06-17",
        "activitytype": "pageviews",
        "activitycount": 1,
        "lastupdate": "2024-06-18T06:16:46-0400"
    },
    {
        "id": 1305896858,
        "objectid": 303593,
        "date": "2024-06-17",
        "activitytype": "pageviews",
        "activitycount": 1,
        "lastupdate": "2024-06-18T06:16:46-0400"
    },
    {
        "id": 132351340,
        "objectid": 237382,
        "date": "2024-06-17",
        "activitytype": "uniquepageviews",
        "activitycount": 1,
        "lastupdate": "2024-06-18T06:16:46-0400"
    },
    {
        "id": 4944492,
        "objectid": 276401,
        "date": "2024-06-17",
        "activitytype": "uniquepageviews",
        "activitycount": 1,
        "lastupdate": "2024-06-18T06:16:46-0400"
    },
    {
        "id": 1669092145,
        "objectid": 290061,
        "date": "2024-06-17",
        "activitytype": "moves",
        "activitycount": 1,
        "lastupdate": "2024-06-18T06:16:46-0400"
    },
    {
        "id": 127893100,
        "objectid": 254909,
        "date": "2024-06-17",
        "activitytype": "uniquepageviews",
        "activitycount": 1,
        "lastupdate": "2024-06-18T06:16:46-0400"
    },
    {
        "id": 1246424218,
        "objectid": 212322,
        "date": "2024-06-17",
        "activitytype": "pageviews",
        "activitycount": 1,
        "lastupdate": "2024-06-18T06:16:46-0400"
    },
    {
        "id": 3754860,
        "objectid": 279944,
        "date": "2024-06-17",
        "activitytype": "uniquepageviews",
        "activitycount": 1,
        "lastupdate": "2024-06-18T06:16:46-0400"
    },
    {
        "id": 16554860,
        "objectid": 295000,
        "date": "2024-06-17",
        "activitytype": "uniquepageviews",
        "activitycount": 1,
        "lastupdate": "2024-06-18T06:16:46-0400"
    },
    {
        "id": 1308612250,
        "objectid": 297048,
        "date": "2024-06-17",
        "activitytype": "pageviews",
        "activitycount": 1,
        "lastupdate": "2024-06-18T06:16:46-0400"
    },
    {
        "id": 1646216753,
        "objectid": 331288,
        "date": "2024-06-17",
        "activitytype": "moves",
        "activitycount": 1,
        "lastupdate": "2024-06-18T06:16:46-0400"
    },
    {
        "id": 1684638513,
        "objectid": 227541,
        "date": "2024-06-17",
        "activitytype": "moves",
        "activitycount": 1,
        "lastupdate": "2024-06-18T06:16:46-0400"
    },
    {
        "id": 1278291354,
        "objectid": 345763,
        "date": "2024-06-17",
        "activitytype": "pageviews",
        "activitycount": 1,
        "lastupdate": "2024-06-18T06:16:46-0400"
    },
    {
        "id": 1255125914,
        "objectid": 243773,
        "date": "2024-06-17",
        "activitytype": "pageviews",
        "activitycount": 1,
        "lastupdate": "2024-06-18T06:16:46-0400"
    },
    {
        "id": 20240236,
        "objectid": 346132,
        "date": "2024-06-17",
        "activitytype": "uniquepageviews",
        "activitycount": 1,
        "lastupdate": "2024-06-18T06:16:46-0400"
    },
    {
        "id": 1672279089,
        "objectid": 310698,
        "date": "2024-06-17",
        "activitytype": "moves",
        "activitycount": 1,
        "lastupdate": "2024-06-18T06:16:46-0400"
    },
    {
        "id": 123687020,
        "objectid": 205715,
        "date": "2024-06-17",
        "activitytype": "uniquepageviews",
        "activitycount": 1,
        "lastupdate": "2024-06-18T06:16:46-0400"
    },
    {
        "id": 133689964,
        "objectid": 232241,
        "date": "2024-06-17",
        "activitytype": "uniquepageviews",
        "activitycount": 1,
        "lastupdate": "2024-06-18T06:16:46-0400"
    },
    {
        "id": 1244967579,
        "objectid": 213820,
        "date": "2024-06-17",
        "activitytype": "pageviews",
        "activitycount": 2,
        "lastupdate": "2024-06-18T06:16:46-0400"
    }
]