[
    {
        "id": 12713832,
        "objectid": 310588,
        "date": "2024-06-17",
        "activitytype": "uniquepageviews",
        "activitycount": 5,
        "lastupdate": "2024-06-18T06:16:46-0400"
    },
    {
        "id": 1299420058,
        "objectid": 263197,
        "date": "2024-06-17",
        "activitytype": "pageviews",
        "activitycount": 1,
        "lastupdate": "2024-06-18T06:16:46-0400"
    },
    {
        "id": 1308437914,
        "objectid": 297635,
        "date": "2024-06-17",
        "activitytype": "pageviews",
        "activitycount": 1,
        "lastupdate": "2024-06-18T06:16:46-0400"
    },
    {
        "id": 1308198298,
        "objectid": 298507,
        "date": "2024-06-17",
        "activitytype": "pageviews",
        "activitycount": 1,
        "lastupdate": "2024-06-18T06:16:46-0400"
    },
    {
        "id": 1278270106,
        "objectid": 345940,
        "date": "2024-06-17",
        "activitytype": "pageviews",
        "activitycount": 1,
        "lastupdate": "2024-06-18T06:16:46-0400"
    },
    {
        "id": 13558380,
        "objectid": 307745,
        "date": "2024-06-17",
        "activitytype": "uniquepageviews",
        "activitycount": 1,
        "lastupdate": "2024-06-18T06:16:46-0400"
    },
    {
        "id": 1234640794,
        "objectid": 57489,
        "date": "2024-06-17",
        "activitytype": "pageviews",
        "activitycount": 1,
        "lastupdate": "2024-06-18T06:16:46-0400"
    },
    {
        "id": 1257661594,
        "objectid": 229866,
        "date": "2024-06-17",
        "activitytype": "pageviews",
        "activitycount": 1,
        "lastupdate": "2024-06-18T06:16:46-0400"
    },
    {
        "id": 118048364,
        "objectid": 226693,
        "date": "2024-06-17",
        "activitytype": "uniquepageviews",
        "activitycount": 1,
        "lastupdate": "2024-06-18T06:16:46-0400"
    },
    {
        "id": 17180268,
        "objectid": 359141,
        "date": "2024-06-17",
        "activitytype": "uniquepageviews",
        "activitycount": 1,
        "lastupdate": "2024-06-18T06:16:46-0400"
    },
    {
        "id": 1260991132,
        "objectid": 155324,
        "date": "2024-06-17",
        "activitytype": "pageviews",
        "activitycount": 3,
        "lastupdate": "2024-06-18T06:16:46-0400"
    },
    {
        "id": 1254513050,
        "objectid": 242135,
        "date": "2024-06-17",
        "activitytype": "pageviews",
        "activitycount": 1,
        "lastupdate": "2024-06-18T06:16:46-0400"
    },
    {
        "id": 1295195290,
        "objectid": 279698,
        "date": "2024-06-17",
        "activitytype": "pageviews",
        "activitycount": 1,
        "lastupdate": "2024-06-18T06:16:46-0400"
    },
    {
        "id": 1278656922,
        "objectid": 344399,
        "date": "2024-06-17",
        "activitytype": "pageviews",
        "activitycount": 1,
        "lastupdate": "2024-06-18T06:16:46-0400"
    },
    {
        "id": 1672123441,
        "objectid": 310218,
        "date": "2024-06-17",
        "activitytype": "moves",
        "activitycount": 1,
        "lastupdate": "2024-06-18T06:16:46-0400"
    },
    {
        "id": 84020076,
        "objectid": 97992,
        "date": "2024-06-17",
        "activitytype": "uniquepageviews",
        "activitycount": 1,
        "lastupdate": "2024-06-18T06:16:46-0400"
    },
    {
        "id": 131909228,
        "objectid": 237573,
        "date": "2024-06-17",
        "activitytype": "uniquepageviews",
        "activitycount": 1,
        "lastupdate": "2024-06-18T06:16:46-0400"
    },
    {
        "id": 1656354097,
        "objectid": 370859,
        "date": "2024-06-17",
        "activitytype": "moves",
        "activitycount": 1,
        "lastupdate": "2024-06-18T06:16:46-0400"
    },
    {
        "id": 16042348,
        "objectid": 296970,
        "date": "2024-06-17",
        "activitytype": "uniquepageviews",
        "activitycount": 1,
        "lastupdate": "2024-06-18T06:16:46-0400"
    },
    {
        "id": 1278297242,
        "objectid": 345802,
        "date": "2024-06-17",
        "activitytype": "pageviews",
        "activitycount": 1,
        "lastupdate": "2024-06-18T06:16:46-0400"
    },
    {
        "id": 4055404,
        "objectid": 278818,
        "date": "2024-06-17",
        "activitytype": "uniquepageviews",
        "activitycount": 1,
        "lastupdate": "2024-06-18T06:16:46-0400"
    },
    {
        "id": 1670452529,
        "objectid": 294987,
        "date": "2024-06-17",
        "activitytype": "moves",
        "activitycount": 1,
        "lastupdate": "2024-06-18T06:16:46-0400"
    },
    {
        "id": 1245393562,
        "objectid": 216252,
        "date": "2024-06-17",
        "activitytype": "pageviews",
        "activitycount": 1,
        "lastupdate": "2024-06-18T06:16:46-0400"
    },
    {
        "id": 1255340954,
        "objectid": 238965,
        "date": "2024-06-17",
        "activitytype": "pageviews",
        "activitycount": 1,
        "lastupdate": "2024-06-18T06:16:46-0400"
    },
    {
        "id": 6150252,
        "objectid": 270619,
        "date": "2024-06-17",
        "activitytype": "uniquepageviews",
        "activitycount": 1,
        "lastupdate": "2024-06-18T06:16:46-0400"
    },
    {
        "id": 1278288794,
        "objectid": 345773,
        "date": "2024-06-17",
        "activitytype": "pageviews",
        "activitycount": 1,
        "lastupdate": "2024-06-18T06:16:46-0400"
    },
    {
        "id": 125030505,
        "objectid": 200467,
        "date": "2024-06-17",
        "activitytype": "uniquepageviews",
        "activitycount": 4,
        "lastupdate": "2024-06-18T06:16:46-0400"
    },
    {
        "id": 15862124,
        "objectid": 298698,
        "date": "2024-06-17",
        "activitytype": "uniquepageviews",
        "activitycount": 1,
        "lastupdate": "2024-06-18T06:16:46-0400"
    },
    {
        "id": 128738924,
        "objectid": 250021,
        "date": "2024-06-17",
        "activitytype": "uniquepageviews",
        "activitycount": 1,
        "lastupdate": "2024-06-18T06:16:46-0400"
    },
    {
        "id": 111381356,
        "objectid": 188232,
        "date": "2024-06-17",
        "activitytype": "uniquepageviews",
        "activitycount": 1,
        "lastupdate": "2024-06-18T06:16:46-0400"
    },
    {
        "id": 1307751834,
        "objectid": 296251,
        "date": "2024-06-17",
        "activitytype": "pageviews",
        "activitycount": 1,
        "lastupdate": "2024-06-18T06:16:46-0400"
    },
    {
        "id": 127908716,
        "objectid": 254840,
        "date": "2024-06-17",
        "activitytype": "uniquepageviews",
        "activitycount": 1,
        "lastupdate": "2024-06-18T06:16:46-0400"
    },
    {
        "id": 21415020,
        "objectid": 342535,
        "date": "2024-06-17",
        "activitytype": "uniquepageviews",
        "activitycount": 1,
        "lastupdate": "2024-06-18T06:16:46-0400"
    },
    {
        "id": 5189484,
        "objectid": 275436,
        "date": "2024-06-17",
        "activitytype": "uniquepageviews",
        "activitycount": 1,
        "lastupdate": "2024-06-18T06:16:46-0400"
    },
    {
        "id": 1678621489,
        "objectid": 204005,
        "date": "2024-06-17",
        "activitytype": "moves",
        "activitycount": 1,
        "lastupdate": "2024-06-18T06:16:46-0400"
    },
    {
        "id": 1257835674,
        "objectid": 233090,
        "date": "2024-06-17",
        "activitytype": "pageviews",
        "activitycount": 1,
        "lastupdate": "2024-06-18T06:16:46-0400"
    },
    {
        "id": 1250527386,
        "objectid": 261638,
        "date": "2024-06-17",
        "activitytype": "pageviews",
        "activitycount": 1,
        "lastupdate": "2024-06-18T06:16:46-0400"
    },
    {
        "id": 126602348,
        "objectid": 259855,
        "date": "2024-06-17",
        "activitytype": "uniquepageviews",
        "activitycount": 1,
        "lastupdate": "2024-06-18T06:16:46-0400"
    },
    {
        "id": 4949612,
        "objectid": 276293,
        "date": "2024-06-17",
        "activitytype": "uniquepageviews",
        "activitycount": 1,
        "lastupdate": "2024-06-18T06:16:46-0400"
    },
    {
        "id": 1254652826,
        "objectid": 245749,
        "date": "2024-06-17",
        "activitytype": "pageviews",
        "activitycount": 1,
        "lastupdate": "2024-06-18T06:16:46-0400"
    },
    {
        "id": 1308292762,
        "objectid": 298360,
        "date": "2024-06-17",
        "activitytype": "pageviews",
        "activitycount": 1,
        "lastupdate": "2024-06-18T06:16:46-0400"
    },
    {
        "id": 132008812,
        "objectid": 238216,
        "date": "2024-06-17",
        "activitytype": "uniquepageviews",
        "activitycount": 1,
        "lastupdate": "2024-06-18T06:16:46-0400"
    },
    {
        "id": 93636972,
        "objectid": 124938,
        "date": "2024-06-17",
        "activitytype": "uniquepageviews",
        "activitycount": 1,
        "lastupdate": "2024-06-18T06:16:46-0400"
    },
    {
        "id": 1255580826,
        "objectid": 237866,
        "date": "2024-06-17",
        "activitytype": "pageviews",
        "activitycount": 1,
        "lastupdate": "2024-06-18T06:16:46-0400"
    },
    {
        "id": 9369196,
        "objectid": 324149,
        "date": "2024-06-17",
        "activitytype": "uniquepageviews",
        "activitycount": 1,
        "lastupdate": "2024-06-18T06:16:46-0400"
    },
    {
        "id": 21336428,
        "objectid": 342354,
        "date": "2024-06-17",
        "activitytype": "uniquepageviews",
        "activitycount": 1,
        "lastupdate": "2024-06-18T06:16:46-0400"
    },
    {
        "id": 1280207514,
        "objectid": 342500,
        "date": "2024-06-17",
        "activitytype": "pageviews",
        "activitycount": 1,
        "lastupdate": "2024-06-18T06:16:46-0400"
    },
    {
        "id": 1658571057,
        "objectid": 379543,
        "date": "2024-06-17",
        "activitytype": "moves",
        "activitycount": 1,
        "lastupdate": "2024-06-18T06:16:46-0400"
    },
    {
        "id": 1246414490,
        "objectid": 212296,
        "date": "2024-06-17",
        "activitytype": "pageviews",
        "activitycount": 1,
        "lastupdate": "2024-06-18T06:16:46-0400"
    },
    {
        "id": 8145516,
        "objectid": 262281,
        "date": "2024-06-17",
        "activitytype": "uniquepageviews",
        "activitycount": 1,
        "lastupdate": "2024-06-18T06:16:46-0400"
    },
    {
        "id": 1652792627,
        "objectid": 365251,
        "date": "2024-06-17",
        "activitytype": "moves",
        "activitycount": 3,
        "lastupdate": "2024-06-18T06:16:46-0400"
    },
    {
        "id": 1278865306,
        "objectid": 347745,
        "date": "2024-06-17",
        "activitytype": "pageviews",
        "activitycount": 1,
        "lastupdate": "2024-06-18T06:16:46-0400"
    },
    {
        "id": 123973999,
        "objectid": 204658,
        "date": "2024-06-17",
        "activitytype": "uniquepageviews",
        "activitycount": 2,
        "lastupdate": "2024-06-18T06:16:46-0400"
    },
    {
        "id": 131975020,
        "objectid": 237828,
        "date": "2024-06-17",
        "activitytype": "uniquepageviews",
        "activitycount": 1,
        "lastupdate": "2024-06-18T06:16:46-0400"
    },
    {
        "id": 1252503450,
        "objectid": 249889,
        "date": "2024-06-17",
        "activitytype": "pageviews",
        "activitycount": 1,
        "lastupdate": "2024-06-18T06:16:46-0400"
    },
    {
        "id": 1296344474,
        "objectid": 275243,
        "date": "2024-06-17",
        "activitytype": "pageviews",
        "activitycount": 1,
        "lastupdate": "2024-06-18T06:16:46-0400"
    },
    {
        "id": 20824428,
        "objectid": 344322,
        "date": "2024-06-17",
        "activitytype": "uniquepageviews",
        "activitycount": 1,
        "lastupdate": "2024-06-18T06:16:46-0400"
    },
    {
        "id": 1672287793,
        "objectid": 310344,
        "date": "2024-06-17",
        "activitytype": "moves",
        "activitycount": 1,
        "lastupdate": "2024-06-18T06:16:46-0400"
    },
    {
        "id": 1255527066,
        "objectid": 238172,
        "date": "2024-06-17",
        "activitytype": "pageviews",
        "activitycount": 1,
        "lastupdate": "2024-06-18T06:16:46-0400"
    },
    {
        "id": 1242325402,
        "objectid": 228335,
        "date": "2024-06-17",
        "activitytype": "pageviews",
        "activitycount": 1,
        "lastupdate": "2024-06-18T06:16:46-0400"
    },
    {
        "id": 1251859098,
        "objectid": 256596,
        "date": "2024-06-17",
        "activitytype": "pageviews",
        "activitycount": 1,
        "lastupdate": "2024-06-18T06:16:46-0400"
    },
    {
        "id": 126034540,
        "objectid": 262113,
        "date": "2024-06-17",
        "activitytype": "uniquepageviews",
        "activitycount": 1,
        "lastupdate": "2024-06-18T06:16:46-0400"
    },
    {
        "id": 1275576986,
        "objectid": 356428,
        "date": "2024-06-17",
        "activitytype": "pageviews",
        "activitycount": 1,
        "lastupdate": "2024-06-18T06:16:46-0400"
    },
    {
        "id": 1269826714,
        "objectid": 182154,
        "date": "2024-06-17",
        "activitytype": "pageviews",
        "activitycount": 1,
        "lastupdate": "2024-06-18T06:16:46-0400"
    },
    {
        "id": 124854636,
        "objectid": 200162,
        "date": "2024-06-17",
        "activitytype": "uniquepageviews",
        "activitycount": 1,
        "lastupdate": "2024-06-18T06:16:46-0400"
    },
    {
        "id": 1242083738,
        "objectid": 229183,
        "date": "2024-06-17",
        "activitytype": "pageviews",
        "activitycount": 1,
        "lastupdate": "2024-06-18T06:16:46-0400"
    },
    {
        "id": 109750636,
        "objectid": 194154,
        "date": "2024-06-17",
        "activitytype": "uniquepageviews",
        "activitycount": 1,
        "lastupdate": "2024-06-18T06:16:46-0400"
    },
    {
        "id": 12406380,
        "objectid": 311693,
        "date": "2024-06-17",
        "activitytype": "uniquepageviews",
        "activitycount": 1,
        "lastupdate": "2024-06-18T06:16:46-0400"
    },
    {
        "id": 1253278874,
        "objectid": 246794,
        "date": "2024-06-17",
        "activitytype": "pageviews",
        "activitycount": 1,
        "lastupdate": "2024-06-18T06:16:46-0400"
    },
    {
        "id": 1285665946,
        "objectid": 382522,
        "date": "2024-06-17",
        "activitytype": "pageviews",
        "activitycount": 1,
        "lastupdate": "2024-06-18T06:16:46-0400"
    },
    {
        "id": 1278393242,
        "objectid": 345397,
        "date": "2024-06-17",
        "activitytype": "pageviews",
        "activitycount": 1,
        "lastupdate": "2024-06-18T06:16:46-0400"
    },
    {
        "id": 127191916,
        "objectid": 256008,
        "date": "2024-06-17",
        "activitytype": "uniquepageviews",
        "activitycount": 1,
        "lastupdate": "2024-06-18T06:16:46-0400"
    },
    {
        "id": 1236461210,
        "objectid": 50536,
        "date": "2024-06-17",
        "activitytype": "pageviews",
        "activitycount": 1,
        "lastupdate": "2024-06-18T06:16:46-0400"
    },
    {
        "id": 131092076,
        "objectid": 240781,
        "date": "2024-06-17",
        "activitytype": "uniquepageviews",
        "activitycount": 1,
        "lastupdate": "2024-06-18T06:16:46-0400"
    },
    {
        "id": 1297741979,
        "objectid": 274038,
        "date": "2024-06-17",
        "activitytype": "pageviews",
        "activitycount": 2,
        "lastupdate": "2024-06-18T06:16:46-0400"
    },
    {
        "id": 13374316,
        "objectid": 307408,
        "date": "2024-06-17",
        "activitytype": "uniquepageviews",
        "activitycount": 1,
        "lastupdate": "2024-06-18T06:16:46-0400"
    },
    {
        "id": 1223976346,
        "objectid": 99307,
        "date": "2024-06-17",
        "activitytype": "pageviews",
        "activitycount": 1,
        "lastupdate": "2024-06-18T06:16:46-0400"
    },
    {
        "id": 109264236,
        "objectid": 196606,
        "date": "2024-06-17",
        "activitytype": "uniquepageviews",
        "activitycount": 1,
        "lastupdate": "2024-06-18T06:16:46-0400"
    },
    {
        "id": 1671494449,
        "objectid": 307621,
        "date": "2024-06-17",
        "activitytype": "moves",
        "activitycount": 1,
        "lastupdate": "2024-06-18T06:16:46-0400"
    },
    {
        "id": 1252754330,
        "objectid": 252941,
        "date": "2024-06-17",
        "activitytype": "pageviews",
        "activitycount": 1,
        "lastupdate": "2024-06-18T06:16:46-0400"
    },
    {
        "id": 132094060,
        "objectid": 238427,
        "date": "2024-06-17",
        "activitytype": "uniquepageviews",
        "activitycount": 1,
        "lastupdate": "2024-06-18T06:16:46-0400"
    },
    {
        "id": 129676908,
        "objectid": 247413,
        "date": "2024-06-17",
        "activitytype": "uniquepageviews",
        "activitycount": 1,
        "lastupdate": "2024-06-18T06:16:46-0400"
    },
    {
        "id": 134174319,
        "objectid": 230293,
        "date": "2024-06-17",
        "activitytype": "uniquepageviews",
        "activitycount": 2,
        "lastupdate": "2024-06-18T06:16:46-0400"
    },
    {
        "id": 13689196,
        "objectid": 306210,
        "date": "2024-06-17",
        "activitytype": "uniquepageviews",
        "activitycount": 1,
        "lastupdate": "2024-06-18T06:16:46-0400"
    },
    {
        "id": 1257831578,
        "objectid": 233330,
        "date": "2024-06-17",
        "activitytype": "pageviews",
        "activitycount": 1,
        "lastupdate": "2024-06-18T06:16:46-0400"
    },
    {
        "id": 1251808666,
        "objectid": 256667,
        "date": "2024-06-17",
        "activitytype": "pageviews",
        "activitycount": 1,
        "lastupdate": "2024-06-18T06:16:46-0400"
    },
    {
        "id": 131260268,
        "objectid": 241180,
        "date": "2024-06-17",
        "activitytype": "uniquepageviews",
        "activitycount": 1,
        "lastupdate": "2024-06-18T06:16:46-0400"
    },
    {
        "id": 117886572,
        "objectid": 227853,
        "date": "2024-06-17",
        "activitytype": "uniquepageviews",
        "activitycount": 1,
        "lastupdate": "2024-06-18T06:16:46-0400"
    },
    {
        "id": 1308383130,
        "objectid": 297945,
        "date": "2024-06-17",
        "activitytype": "pageviews",
        "activitycount": 1,
        "lastupdate": "2024-06-18T06:16:46-0400"
    },
    {
        "id": 1295058330,
        "objectid": 280203,
        "date": "2024-06-17",
        "activitytype": "pageviews",
        "activitycount": 1,
        "lastupdate": "2024-06-18T06:16:46-0400"
    },
    {
        "id": 1297076890,
        "objectid": 276572,
        "date": "2024-06-17",
        "activitytype": "pageviews",
        "activitycount": 1,
        "lastupdate": "2024-06-18T06:16:46-0400"
    },
    {
        "id": 1279173274,
        "objectid": 346412,
        "date": "2024-06-17",
        "activitytype": "pageviews",
        "activitycount": 1,
        "lastupdate": "2024-06-18T06:16:46-0400"
    },
    {
        "id": 123654764,
        "objectid": 205329,
        "date": "2024-06-17",
        "activitytype": "uniquepageviews",
        "activitycount": 1,
        "lastupdate": "2024-06-18T06:16:46-0400"
    },
    {
        "id": 1668160817,
        "objectid": 294723,
        "date": "2024-06-17",
        "activitytype": "moves",
        "activitycount": 1,
        "lastupdate": "2024-06-18T06:16:46-0400"
    },
    {
        "id": 1273835162,
        "objectid": 170656,
        "date": "2024-06-17",
        "activitytype": "pageviews",
        "activitycount": 1,
        "lastupdate": "2024-06-18T06:16:46-0400"
    },
    {
        "id": 84083052,
        "objectid": 98242,
        "date": "2024-06-17",
        "activitytype": "uniquepageviews",
        "activitycount": 1,
        "lastupdate": "2024-06-18T06:16:46-0400"
    },
    {
        "id": 1274150298,
        "objectid": 165491,
        "date": "2024-06-17",
        "activitytype": "pageviews",
        "activitycount": 1,
        "lastupdate": "2024-06-18T06:16:46-0400"
    },
    {
        "id": 13386348,
        "objectid": 307329,
        "date": "2024-06-17",
        "activitytype": "uniquepageviews",
        "activitycount": 1,
        "lastupdate": "2024-06-18T06:16:46-0400"
    },
    {
        "id": 1243782810,
        "objectid": 218384,
        "date": "2024-06-17",
        "activitytype": "pageviews",
        "activitycount": 1,
        "lastupdate": "2024-06-18T06:16:46-0400"
    },
    {
        "id": 1250952858,
        "objectid": 255880,
        "date": "2024-06-17",
        "activitytype": "pageviews",
        "activitycount": 1,
        "lastupdate": "2024-06-18T06:16:46-0400"
    }
]